exoedge_modbus/__init__.py
exoedge_modbus/__version__.py
exoedge_modbus/cli.py
exoedge_modbus/lib.py
test/__init__.py
test/synchronous_server.py
test/test_app_specific_config.py
test/test_lib.py
test/test_read_holding_registers.py
test/test_read_write_coils.py
exoedge_modbus-21.9.15.dist-info/LICENSE
exoedge_modbus-21.9.15.dist-info/METADATA
exoedge_modbus-21.9.15.dist-info/WHEEL
exoedge_modbus-21.9.15.dist-info/entry_points.txt
exoedge_modbus-21.9.15.dist-info/top_level.txt
exoedge_modbus-21.9.15.dist-info/RECORD
