Metadata-Version: 2.1
Name: exoedge-modbus
Version: 21.9.15
Summary: An ExoEdge source for interfacing with Modbus devices.
Home-page: https://github.com/exosite/lib_exoedge_modbus_python
Author: Exosite LLC
Author-email: support@exosite.com
License: Apache 2.0
Keywords: murano exosite iot iiot client gateway modbus tcp rtu
Platform: UNKNOWN
Classifier: Development Status :: 4 - Beta
Classifier: Programming Language :: Python :: 2.7
Classifier: Programming Language :: Python :: 3.5
Classifier: Programming Language :: Python :: 3.6
Classifier: Programming Language :: Python :: 3.7
Classifier: Operating System :: POSIX :: Linux
Classifier: Topic :: System :: Operating System Kernels :: Linux
Classifier: Topic :: Software Development :: Embedded Systems
Classifier: License :: OSI Approved :: Apache Software License
Requires-Python: <4,>=2.7.9
License-File: LICENSE
Requires-Dist: exoedge (>=18.11.17)
Requires-Dist: pymodbus
Requires-Dist: six (>=1.15.0)
